ftsmidi/__init__.py
ftsmidi/midi_sender.py
ftsmidi/midi_format/__init__.py
ftsmidi/midi_format/encode.py
ftsmidi/midi_format/midi_enums.py
fts_rtmidi-0.0.6.dist-info/LICENSE.md
fts_rtmidi-0.0.6.dist-info/METADATA
fts_rtmidi-0.0.6.dist-info/WHEEL
fts_rtmidi-0.0.6.dist-info/top_level.txt
fts_rtmidi-0.0.6.dist-info/RECORD
