Metadata-Version: 2.1
Name: fts-rtmidi
Version: 0.0.6
Summary: A simple class for sending MIDI messages
Author: Ferdinand Oliver M Tonby-Strandborg
Author-email: Ferdinand Oliver M Tonby-Strandborg <ferdinand.tonby.strandborg@gmail.com>
Project-URL: Homepage, https://github.com/Ferdi0412/fts-rtmidi
Classifier: Programming Language :: Python :: 3
Classifier: License :: OSI Approved :: MIT License
Classifier: Operating System :: OS Independent
Requires-Python: >=3.12
License-File: LICENSE.md
Requires-Dist: python-rtmidi >=1.5.8
